limbic/core.py
limbic/interactive.py
limbic/memory.py
limbic/planning.py
limbic/prompts.py
limbic/sessions.py
limbic/stats.py
limbic/tools/analyze.py
limbic/tools/calculator.py
limbic/tools/chat.py
limbic/tools/decorator.py
limbic/tools/inventory.py
limbic/tools/utils.py
limbic/tools/web.py
limbic/utils.py
limbic-0.0.1.dist-info/METADATA
limbic-0.0.1.dist-info/WHEEL
limbic-0.0.1.dist-info/RECORD
