Metadata-Version: 2.3
Name: limbic
Version: 0.0.1
Summary: 
Author: Freddie Vargus
Author-email: freddie@quotientai.co
Requires-Python: >=3.10.13,<4.0
Classifier: Programming Language :: Python :: 3
Classifier: Programming Language :: Python :: 3.11
Classifier: Programming Language :: Python :: 3.12
Classifier: Programming Language :: Python :: 3.13
Requires-Dist: anthropic (>=0.46.0,<0.47.0)
Requires-Dist: beautifulsoup4 (>=4.12.3,<5.0.0)
Requires-Dist: duckduckgo-search (>=8.0.2,<9.0.0)
Requires-Dist: ipython (>=8.32.0,<9.0.0)
Requires-Dist: langchain (>=0.1.12,<0.2.0)
Requires-Dist: langchain-openai (>=0.0.8,<0.0.9)
Requires-Dist: litellm (>=1.61.1,<2.0.0)
Requires-Dist: openai (>=1.62.0,<2.0.0)
Requires-Dist: pdbpp (>=0.10.3,<0.11.0)
Requires-Dist: quotientai (>=0.3.0,<0.4.0)
Requires-Dist: requests (>=2.31.0,<3.0.0)
Requires-Dist: rich (>=13.9.4,<14.0.0)
Requires-Dist: tavily-python (>=0.5.4,<0.6.0)
